Workbook

Sheet 总览
A1: 智能手表数据接入执行计划 — 总览
A2: 项目:沐禾健康(青沐生命科技) | 编制:2026-07-22 | 依据:聚合平台调研报告核实修正版(实际验证于 2026-07-22)
A4: 阶段 | B4: 目标 | C4: 任务数 | D4: 已完成 | E4: 完成率 | F4: 需签字项数
A5: 阶段0 决策确认 | B5: 技术路线/平台选型/预算/合规/华为立项 5 项决策签字 | C5: =COUNTIF(任务清单!$B$2:$B$33,A5) -> 5 | D5: =COUNTIFS(任务清单!$B$2:$B$33,A5,任务清单!$H$2:$H$33,"已完成") -> 0 | E5: =IF(C5=0,0,D5/C5) -> 0 | F5: =COUNTIFS(任务清单!$B$2:$B$33,A5,任务清单!$I$2:$I$33,"是") -> 5
A6: 阶段1 零成本验证 | B6: Validic 免费层+Terra 试用实测,签字定选型 | C6: =COUNTIF(任务清单!$B$2:$B$33,A6) -> 5 | D6: =COUNTIFS(任务清单!$B$2:$B$33,A6,任务清单!$H$2:$H$33,"已完成") -> 1 | E6: =IF(C6=0,0,D6/C6) -> 0.2 | F6: =COUNTIFS(任务清单!$B$2:$B$33,A6,任务清单!$I$2:$I$33,"是") -> 1
A7: 阶段2 华为官方接入 | B7: 按华为审核流程图走完 测试权限→商用验证 全流程 | C7: =COUNTIF(任务清单!$B$2:$B$33,A7) -> 9 | D7: =COUNTIFS(任务清单!$B$2:$B$33,A7,任务清单!$H$2:$H$33,"已完成") -> 0 | E7: =IF(C7=0,0,D7/C7) -> 0 | F7: =COUNTIFS(任务清单!$B$2:$B$33,A7,任务清单!$I$2:$I$33,"是") -> 3
A8: 阶段3 聚合平台接入 | B8: 签约→Garmin 开发者计划→后端 webhook→前端授权→灰度 | C8: =COUNTIF(任务清单!$B$2:$B$33,A8) -> 5 | D8: =COUNTIFS(任务清单!$B$2:$B$33,A8,任务清单!$H$2:$H$33,"已完成") -> 0 | E8: =IF(C8=0,0,D8/C8) -> 0 | F8: =COUNTIFS(任务清单!$B$2:$B$33,A8,任务清单!$I$2:$I$33,"是") -> 2
A9: 阶段4 国产品牌补充 | B9: 小米/vivo/OPPO/宜准商务对接+兜底方案 | C9: =COUNTIF(任务清单!$B$2:$B$33,A9) -> 4 | D9: =COUNTIFS(任务清单!$B$2:$B$33,A9,任务清单!$H$2:$H$33,"已完成") -> 1 | E9: =IF(C9=0,0,D9/C9) -> 0.25 | F9: =COUNTIFS(任务清单!$B$2:$B$33,A9,任务清单!$I$2:$I$33,"是") -> 0
A10: 阶段5 上线验收 | B10: 全链路验证/合规复核/部署/总验收 | C10: =COUNTIF(任务清单!$B$2:$B$33,A10) -> 4 | D10: =COUNTIFS(任务清单!$B$2:$B$33,A10,任务清单!$H$2:$H$33,"已完成") -> 0 | E10: =IF(C10=0,0,D10/C10) -> 0 | F10: =COUNTIFS(任务清单!$B$2:$B$33,A10,任务清单!$I$2:$I$33,"是") -> 2
A11: 合计 | C11: =SUM(C5:C10) -> 32 | D11: =SUM(D5:D10) -> 2 | E11: =IF(C11=0,0,D11/C11) -> 0.0625 | F11: =SUM(F5:F10) -> 13
A13: 使用说明(可编辑单元格)
A14: 1. 在「任务清单」表只需维护:状态(未开始/进行中/已完成/受阻)、签字人、签字日期、备注 四列;其余列为计划基线。
A15: 2. 黄色底纹「需签字确认=是」的任务,完成时必须在「签字确认」表对应行签字。
A16: 3. 本表完成率由公式自动计算,勿手改。
A17: 4. 工期为估算;华为审核时长以官方口径为准,被驳回需重新计时。

Sheet 任务清单
A1: 编号 | B1: 阶段 | C1: 任务 | D1: 详细步骤/说明 | E1: 责任方 | F1: 前置依赖 | G1: 预计工期 | H1: 状态 | I1: 需签字确认 | J1: 签字人 | K1: 签字日期 | L1: 备注
A2: 0.1 | B2: 阶段0 决策确认 | C2: 确认技术路线 | D2: 确认以微信小程序为主。注意:Junction/Validic 的 Apple HealthKit 与 Android Health Connect 均为原生 App SDK,小程序无法嵌入;且 Health Connect 依赖 Google 框架,国行手机(华为/小米/vivo/OPPO)基本不可用。如未来做原生 App 再启用该路线。 | E2: 老板+技术 | F2: — | G2: 1 天 | H2: 未开始 | I2: 是 | L2: 核实结论 2026-07-22
A3: 0.2 | B3: 阶段0 决策确认 | C3: 聚合平台选型 | D3: 推荐 Terra(tryterra.co):实测集成列表含高驰 COROS、松拓 Suunto、华为、Zepp/Amazfit、佳明、Strava,500+ 数据源,$399/月起(年付),SOC2+HIPAA+GDPR。备选 Junction($0.50/用户/月,最低 $300/月,但不支持高驰,小米/松拓仅计划中)。 | E3: 老板+技术 | F3: 0.1 | G3: 2 天 | H3: 未开始 | I3: 是 | L3: 原报告推荐 Junction,核实后改推 Terra
A4: 0.3 | B4: 阶段0 决策确认 | C4: 预算审批 | D4: Terra 约 ¥2,900/月(年付)或 Junction 约 ¥2,200/月起;亦可先走阶段1零成本验证再签约。 | E4: 老板/财务 | F4: 0.2 | G4: 1 天 | H4: 未开始 | I4: 是
A5: 0.4 | B5: 阶段0 决策确认 | C5: 数据合规立项 | D5: 聚合平台服务器均在海外,运动健康数据属 PIPL 敏感个人信息,出境需安全评估/标准合同+单独同意。商用前必须完成,建议与阶段1并行启动。 | E5: 法务/老板 | F5: 0.1 | G5: 2-4 周 | H5: 未开始 | I5: 是 | L5: 原报告未提,属硬性前置
A6: 0.5 | B6: 阶段0 决策确认 | C6: 华为官方接入立项 | D6: 华为运动健康服务现面向鸿蒙应用(需创建 HarmonyOS 应用/元服务取得 APP ID),纯小程序不能直接用。确认是否立项做鸿蒙端采集+云端同步。 | E6: 老板+技术 | F6: 0.1 | G6: 1 天 | H6: 未开始 | I6: 是
A7: 1.1 | B7: 阶段1 零成本验证 | C7: 注册 Validic 免费开发者层 | D7: 2026-04 起 Validic 开放免费自助注册(无合同/无信用卡),700+ 设备。沙盒验证数据字段与质量。注意:2026-06 已被 ChartSpan 收购,长期政策留意。 | E7: 后端 | F7: 0.2 | G7: 3 天 | H7: 未开始 | I7: 否 | L7: validic.com/inform-signup
A8: 1.2 | B8: 阶段1 零成本验证 | C8: 注册 Terra 试用 | D8: dashboard.tryterra.co 注册,实测高驰/松拓/华为/佳明连通性、数据字段、webhook 推送。 | E8: 后端 | F8: 0.2 | G8: 3 天 | H8: 未开始 | I8: 否
A9: 1.3 | B9: 阶段1 零成本验证 | C9: 微信运动数据复核 | D9: 小程序 wx.getWeRunData 为标准能力,无需申请周期,项目已接入(utils/werun.ts),回归验证即可。 | E9: 前端 | F9: — | G9: 0.5 天 | H9: 已完成 | I9: 否 | L9: 示例行:已有能力
A10: 1.4 | B10: 阶段1 零成本验证 | C10: 文件导入兜底回归 | D10: 回归现有佳明 FIT / 华为 TCX(V0.2.47,1633 活动)/ COROS FIT 导入链路,作为无 API 品牌兜底。 | E10: 后端 | F10: — | G10: 1 天 | H10: 未开始 | I10: 否
A11: 1.5 | B11: 阶段1 零成本验证 | C11: 输出验证报告并确认选型 | D11: 汇总 1.1-1.4 实测结果,老板签字确认最终平台与签约档位。 | E11: 技术负责人 | F11: 1.1-1.4 | G11: 1 天 | H11: 未开始 | I11: 是 | L11: 阶段1里程碑
A12: 2.1 | B12: 阶段2 华为官方接入 | C12: 注册联盟开发者账号 | D12: developer.huawei.com 注册华为开发者联盟账号(企业类型)。 | E12: 后端 | F12: 0.5 | G12: 0.5 天 | H12: 未开始 | I12: 否
A13: 2.2 | B13: 阶段2 华为官方接入 | C13: 企业实名认证 | D13: 推荐企业对公账号打款认证:提交→华为向对公账户打款→财务查询金额→回填验证。评审约 3 个工作日(人工审核认证约 2 个工作日)。 | E13: 后端+财务 | F13: 2.1 | G13: 3 工作日 | H13: 未开始 | I13: 否 | L13: 需财务配合查打款金额
A14: 2.3 | B14: 阶段2 华为官方接入 | C14: 创建 HarmonyOS 应用/元服务 | D14: AppGallery Connect 创建鸿蒙应用/元服务,取得 APP ID。 | E14: 后端 | F14: 2.2 | G14: 0.5 天 | H14: 未开始 | I14: 否
A15: 2.4 | B15: 阶段2 华为官方接入 | C15: 准备测试权限申请材料 | D15: 三件套:①运动健康服务申请资料清单 ②企业介绍材料 ③隐私政策链接(需含华为数据使用声明)。内部评审后提交。 | E15: 后端+法务 | F15: 2.3 | G15: 3 天 | H15: 未开始 | I15: 是 | L15: 材料定稿需签字
A16: 2.5 | B16: 阶段2 华为官方接入 | C16: 提交测试权限申请 | D16: 申请数据测试权限,人工审核:重点/战略伙伴≤5 个工作日,优质伙伴≤10 个工作日(官方通用口径约 15 个工作日)。测试期用户上限 100 人。 | E16: 后端 | F16: 2.4 | G16: 5-15 工作日 | H16: 未开始 | I16: 否 | L16: 被驳回需修改重审
A17: 2.6 | B17: 阶段2 华为官方接入 | C17: 开发联调 | D17: 鸿蒙端采集运动健康数据→同步到 qingmulife.cn 后端→小程序展示。dataSource 新增 huawei_kit。 | E17: 前后端 | F17: 2.5 | G17: 2-3 周 | H17: 未开始 | I17: 否
A18: 2.7 | B18: 阶段2 华为官方接入 | C18: 准备商用验证材料 | D18: 两件套:①举证材料.zip(功能演示视频+自检截图) ②应用上线 Checklist。内部评审后提交。 | E18: 后端 | F18: 2.6 | G18: 3 天 | H18: 未开始 | I18: 是 | L18: 材料定稿需签字
A19: 2.8 | B19: 阶段2 华为官方接入 | C19: 提交验证权限申请并商用 | D19: 人工审核:重点/战略伙伴≤7 个工作日,优质伙伴≤15 个工作日。通过后解除 100 用户限制,正式商用。 | E19: 后端 | F19: 2.7 | G19: 7-15 工作日 | H19: 未开始 | I19: 否
A20: 2.9 | B20: 阶段2 华为官方接入 | C20: 阶段验收 | D20: 华为数据全链路真机验证通过,老板签字验收。 | E20: 老板 | F20: 2.8 | G20: 0.5 天 | H20: 未开始 | I20: 是 | L20: 阶段2里程碑
A21: 3.1 | B21: 阶段3 聚合平台接入 | C21: 商务签约 | D21: 与选定平台(Terra/Junction)签约:合同、发票(海外服务商注意代扣税)、支付方式。 | E21: 老板/财务 | F21: 1.5,0.4 | G21: 1 周 | H21: 未开始 | I21: 是
A22: 3.2 | B22: 阶段3 聚合平台接入 | C22: 申请 Garmin 开发者计划 | D22: 佳明需单独申请 Garmin Connect Developer Program(免费,商业资质审核),通过后在聚合平台配置 BYOO 凭证。 | E22: 后端 | F22: 3.1 | G22: 2-4 周 | H22: 未开始 | I22: 否 | L22: developer.garmin.com
A23: 3.3 | B23: 阶段3 聚合平台接入 | C23: 后端接入 | D23: webhook 接收+数据标准化映射到 Checkin/睡眠/心率表,dataSource 扩展(terra_garmin/terra_coros 等),幂等去重(复用 V0.2.60 范式)。 | E23: 后端 | F23: 3.1 | G23: 1-2 周 | H23: 未开始 | I23: 否
A24: 3.4 | B24: 阶段3 聚合平台接入 | C24: 前端授权流程 | D24: 小程序内引导→H5 页完成平台 OAuth 授权(复用 V0.2.63 H5 fallback 范式)→回小程序查看数据。 | E24: 前端 | F24: 3.3 | G24: 1 周 | H24: 未开始 | I24: 否
A25: 3.5 | B25: 阶段3 聚合平台接入 | C25: 灰度测试与验收 | D25: 内部 10-20 人多品牌手表实测→数据准确性核对→老板签字验收。 | E25: 全员 | F25: 3.4 | G25: 1 周 | H25: 未开始 | I25: 是 | L25: 阶段3里程碑
A26: 4.1 | B26: 阶段4 国产品牌补充 | C26: 小米商务对接 | D26: 小米健康云开放平台目前仅对生态链企业及合作伙伴开放,需商务渠道对接,非自助申请。 | E26: 商务 | F26: 3.5 | G26: 不确定 | H26: 未开始 | I26: 否 | L26: 核实修正:原报告称2-4周自助申请有误
A27: 4.2 | B27: 阶段4 国产品牌补充 | C27: vivo/OPPO 商务对接 | D27: 两家健康开放平台未见公开自助申请入口,大概率合作伙伴制,商务对接。 | E27: 商务 | F27: 3.5 | G27: 不确定 | H27: 未开始 | I27: 否
A28: 4.3 | B28: 阶段4 国产品牌补充 | C28: 宜准邮件对接 | D28: 无公开 API,邮件商务洽谈。 | E28: 商务 | F28: 3.5 | G28: 不确定 | H28: 未开始 | I28: 否
A29: 4.4 | B29: 阶段4 国产品牌补充 | C29: 无 API 品牌兜底 | D29: 截图识别(已有 interpret screenshot V0.2.57-63)+ 文件导入,覆盖一切拿不到 API 的品牌。 | E29: 后端 | F29: — | G29: 已具备 | H29: 已完成 | I29: 否
A30: 5.1 | B30: 阶段5 上线验收 | C30: 全链路真机验证 | D30: 各品牌手表→数据入库→今日页/月报/AI 教练消费,全链路真机回归。 | E30: 测试 | F30: 3.5,2.9 | G30: 1 周 | H30: 未开始 | I30: 否
A31: 5.2 | B31: 阶段5 上线验收 | C31: 合规复核 | D31: 隐私政策更新(列明第三方平台与出境情况)、用户单独同意弹窗、撤回授权入口。法务签字。 | E31: 法务 | F31: 0.4,5.1 | G31: 3 天 | H31: 未开始 | I31: 是
A32: 5.3 | B32: 阶段5 上线验收 | C32: 生产部署与监控 | D32: 部署、告警、数据同步失败重试监控。 | E32: 后端 | F32: 5.1 | G32: 2 天 | H32: 未开始 | I32: 否
A33: 5.4 | B33: 阶段5 上线验收 | C33: 项目总验收 | D33: 老板总验收签字,项目转入运营。 | E33: 老板 | F33: 5.2,5.3 | G33: 0.5 天 | H33: 未开始 | I33: 是 | L33: 项目里程碑

Sheet 签字确认
A1: 关键决策与里程碑签字确认表
A3: 编号 | B3: 事项 | C3: 确认内容 | D3: 责任人 | E3: 负责人签字/日期 | F3: 审批人签字/日期 | G3: 状态
A4: 0.1 | B4: 技术路线确认 | C4: 以微信小程序为主,原生 App SDK 路线暂缓 | D4: 技术负责人 | G4: 未签
A5: 0.2 | B5: 聚合平台选型 | C5: 选定 Terra / Junction / Validic(圈选)及套餐档位 | D5: 老板 | G5: 未签
A6: 0.3 | B6: 预算审批 | C6: 月度订阅费用批准:¥______/月 | D6: 老板/财务 | G6: 未签
A7: 0.4 | B7: 合规立项 | C7: 健康数据出境 PIPL 评估方案批准 | D7: 法务 | G7: 未签
A8: 0.5 | B8: 华为接入立项 | C8: 鸿蒙应用开发立项批准 | D8: 老板 | G8: 未签
A9: 1.5 | B9: 阶段1验收 | C9: 零成本验证报告确认,最终选型定稿 | D9: 老板 | G9: 未签
A10: 2.4 | B10: 华为测试材料定稿 | C10: 申请资料清单/企业介绍/隐私政策三件套 | D10: 技术+法务 | G10: 未签
A11: 2.7 | B11: 华为商用材料定稿 | C11: 举证材料.zip + 上线 Checklist | D11: 技术负责人 | G11: 未签
A12: 2.9 | B12: 阶段2验收 | C12: 华为数据全链路验证通过 | D12: 老板 | G12: 未签
A13: 3.1 | B13: 聚合平台签约 | C13: 合同条款与付款方式确认 | D13: 老板/财务 | G13: 未签
A14: 3.5 | B14: 阶段3验收 | C14: 聚合平台灰度测试通过 | D14: 老板 | G14: 未签
A15: 5.2 | B15: 合规复核 | C15: 隐私政策/用户同意/撤回授权上线确认 | D15: 法务 | G15: 未签
A16: 5.4 | B16: 项目总验收 | C16: 全部品牌接入验收,项目转运营 | D16: 老板 | G16: 未签
A18: 说明:黄色栏为手写/电子签字区;「状态」改为 已签 后,请同步更新「任务清单」对应行。
